meshtastic_prometheus_exporter/__about__.py
meshtastic_prometheus_exporter/__init__.py
meshtastic_prometheus_exporter/__main__.py
meshtastic_prometheus_exporter/metrics.py
meshtastic_prometheus_exporter/neighborinfo.py
meshtastic_prometheus_exporter/nodeinfo.py
meshtastic_prometheus_exporter/telemetry.py
meshtastic_prometheus_exporter/util.py
meshtastic_prometheus_exporter-2.5.dist-info/METADATA
meshtastic_prometheus_exporter-2.5.dist-info/WHEEL
meshtastic_prometheus_exporter-2.5.dist-info/entry_points.txt
meshtastic_prometheus_exporter-2.5.dist-info/licenses/LICENSE.txt
meshtastic_prometheus_exporter-2.5.dist-info/RECORD
