Metadata-Version: 2.4
Name: meshtastic-prometheus-exporter
Version: 2.5
Project-URL: Documentation, https://github.com/Artiom Mocrenco/meshtastic-prometheus-exporter#readme
Project-URL: Issues, https://github.com/Artiom Mocrenco/meshtastic-prometheus-exporter/issues
Project-URL: Source, https://github.com/Artiom Mocrenco/meshtastic-prometheus-exporter
Author-email: Artiom Mocrenco <artiom.mocrenco@gmail.com>
License-Expression: MIT
License-File: LICENSE.txt
Classifier: Development Status :: 4 - Beta
Classifier: Programming Language :: Python :: 3.12
Requires-Python: >=3.8
Requires-Dist: cachetools==6.2.4
Requires-Dist: meshtastic==2.7.5
Requires-Dist: opentelemetry-api==1.36.0
Requires-Dist: opentelemetry-exporter-prometheus==0.57b0
Requires-Dist: opentelemetry-sdk==1.36.0
Requires-Dist: paho-mqtt==2.1.0
Requires-Dist: pypubsub==4.0.3
Requires-Dist: sentry-sdk==2.46.0
